[{"fecha":"2025-02-23T20:00:00.000+00:00","nombreCliente":"Marianela Montalvo","numeroCuenta":"225487","tipo":"Corriente","saldoInicial":100.0,"estado":true,"movimiento":-575.0,"saldoDisponible":1425.0},{"fecha":"2025-02-23T14:00:00.000+00:00","nombreCliente":"Juan Osorio","numeroCuenta":"495878","tipo":"Ahorros","saldoInicial":0.0,"estado":true,"movimiento":600.0,"saldoDisponible":700.0},{"fecha":"2025-02-23T15:10:00.000+00:00","nombreCliente":"Marianela Montalvo","numeroCuenta":"496825","tipo":"Ahorros","saldoInicial":540.0,"estado":true,"movimiento":150.0,"saldoDisponible":150.0},{"fecha":"2025-02-23T15:30:00.000+00:00","nombreCliente":"Juan Osorio","numeroCuenta":"495878","tipo":"Ahorros","saldoInicial":0.0,"estado":true,"movimiento":540.0,"saldoDisponible":0.0}]